np2d/__init__.py
np2d/base.py
np2d/basic.py
np2d/random.py
np2d/tests/__init__.py
np2d/tests/test_basic.py
np2d-0.1.1.dist-info/DESCRIPTION.rst
np2d-0.1.1.dist-info/METADATA
np2d-0.1.1.dist-info/RECORD
np2d-0.1.1.dist-info/WHEEL
np2d-0.1.1.dist-info/metadata.json
np2d-0.1.1.dist-info/top_level.txt
