Metadata-Version: 2.0
Name: np2d
Version: 0.1.1
Summary: Common 2-D NumPy operations.
Home-page: https://github.com/Zsailer/np2d
Author: Zach Sailer
Author-email: zachsailer@gmail.com
License: MIT
Keywords: numpy,2d,arrays
Platform: UNKNOWN
Classifier: Development Status :: 3 - Alpha
Classifier: Programming Language :: Python :: 3
Classifier: Programming Language :: Python :: 3.2
Classifier: Programming Language :: Python :: 3.3
Classifier: Programming Language :: Python :: 3.4
